{
	"credit": "Made with Blockbench",
	"texture_size": [64, 64],
	"textures": {
		"1": "bin_interior_texture"
	},
	"elements": [
		{
			"from": [2, -16, 1],
			"to": [14, 1, 2],
			"rotation": {"angle": 0, "axis": "y", "origin": [0, 0, 1]},
			"faces": {
				"north": {"uv": [0.5, 0, 3.5, 4.25], "texture": "#1"},
				"east": {"uv": [0, 0, 0.25, 4.25], "texture": "#1"},
				"south": {"uv": [0.5, 0, 3.5, 4.25], "texture": "#1"},
				"west": {"uv": [0, 0, 0.25, 4.25], "texture": "#1"},
				"up": {"uv": [0, 0, 3, 0.25], "texture": "#1"},
				"down": {"uv": [0, 0, 3, 0.25], "texture": "#1"}
			}
		},
		{
			"from": [0, -16, 0],
			"to": [16, 1, 1],
			"faces": {
				"north": {"uv": [4, 0, 8, 4.25], "texture": "#1"},
				"east": {"uv": [0, 0, 0.25, 4.25], "texture": "#1"},
				"south": {"uv": [4, 0, 8, 4.25], "texture": "#1"},
				"west": {"uv": [0, 0, 0.25, 4.25], "texture": "#1"},
				"up": {"uv": [12, 0.25, 8, 0], "texture": "#1"},
				"down": {"uv": [12, 4, 8, 8], "texture": "#1"}
			}
		},
		{
			"from": [0, 1, 0],
			"to": [16, 8, 1],
			"faces": {
				"north": {"uv": [4, 8.5, 8, 10.25], "texture": "#1"},
				"east": {"uv": [4, 8.5, 4.25, 10.25], "texture": "#1"},
				"south": {"uv": [4, 8.5, 8, 10.25], "texture": "#1"},
				"west": {"uv": [4, 8.5, 4.25, 10.25], "texture": "#1"},
				"up": {"uv": [12, 8.25, 8, 8], "texture": "#1"},
				"down": {"uv": [4, 8.5, 0, 12.5], "texture": "#1"}
			}
		}
	]
}